pubcrank_cli-0.3.0.dist-info/METADATA
pubcrank_cli-0.3.0.dist-info/WHEEL
pubcrank_cli-0.3.0.dist-info/entry_points.txt
pubcrank_cli/__init__.py
pubcrank_cli/main.py
pubsite/__init__.py
pubsite/asgi.py
pubsite/settings.py
pubsite/urls.py
pubsite/wsgi.py
pubcrank_cli-0.3.0.dist-info/RECORD
