Metadata-Version: 2.1
Name: pubcrank-cli
Version: 0.3.0
Summary: PubCrank CMS CLI
Author-Email: Paul Bailey <paul@neutron.studio>
License: BSD 3-Clause
Requires-Python: >=3.13
Requires-Dist: django>=5.2.1
Requires-Dist: pubcrank-django-app>=0.5.0
